{
  "tasks": [
    {
      "title": "asdfsadfasd",
      "description": "asdfasdfasdafadf",
      "id": 1
    },
    {
      "title": "Hello",
      "description": "Do something",
      "id": 2
    },
    {
      "title": "asdf",
      "description": "asdfasdf",
      "id": 3
    },
    {
      "title": "Hello",
      "description": "Do anything",
      "id": 4
    },
    {
      "title": "Ilyas",
      "description": "asdfdasf",
      "id": 5
    },
    {
      "title": "Ilyas222",
      "description": "weqwerqwer",
      "id": 6
    },
    {
      "title": "Kia",
      "description": "Driver Kia Taxi",
      "id": 7
    },
    {
      "title": "asdfasdfasdf",
      "description": "adsfasdfasdfasdfa",
      "id": 8
    },
    {
      "title": "asdfasdfasdfasdf",
      "description": "asdfasdfasdfasdfafs",
      "id": 9
    },
    {
      "title": "First",
      "description": "Do minecraft game",
      "status": "in Work",
      "id": 10
    }
  ]
}